setup.py
ticklingtikale/__init__.py
ticklingtikale.egg-info/PKG-INFO
ticklingtikale.egg-info/SOURCES.txt
ticklingtikale.egg-info/dependency_links.txt
ticklingtikale.egg-info/not-zip-safe
ticklingtikale.egg-info/top_level.txt