Metadata-Version: 1.0
Name: ticklingtikale
Version: 0.1
Summary: The Funniest joke in the world
Home-page: http://github.com/sahil/ticklingtikale
Author: Funny Man
Author-email: funny@laughter.org
License: MIT
Platform: UNKNOWN
